{"21838":[{"meter":"2/4","mode":"Dmajor","abc":"d2ABABc2|d2A2B2c2|d2cdedcB|"},{"meter":"2/4","mode":"Dmajor","abc":"|:dc|BcBAGdcB|ABAGF2BA|GAGFEFGE|"},{"meter":"2/4","mode":"Dmajor","abc":"d2>A2 BABc|d2A2 B2c2|d2cd edcB|A2>F2 AGFE|\nD2>E2 FEFG|A2>B2 cdcA|(3BcBA2- A4-|A4- A2DE||\n|:F2>D2 FDFA|GFED C2CE|G2>E2 GEGB|AGFE D2DE|\nF2>D2 FDFA|GFED CDEF|GFED CDEF|AGFE D2DE|\nF2>D2 FDFA|GFED C2CE|G2>E2 GEGB|AGFE D2DE|\nF2>D2 FDFA|GFED C4|G2F2 A2G2|[M:3/4] E2C2 D4- D2DF:|\n|:AGFE AGFE|B2AF DFDF|AGFE AGFE|1 D2CE D2DF:|2 D4- D2BA||\n|:GAGF EBAG|FGFE D2GF|EFED CGFE|(3GAGF2- F2BA|\nGAGF EBAG|FGFE D2GF|EFED CGFE|1 D4- D2BA:|2 D8||"},{"meter":"2/4","mode":"Dmajor","abc":"d>A B/2A/2B/2c/2|dA Bc|dc/2d/2 e/2d/2c/2B/2|A>F A/2G/2F/2E/2|\nD>E F/2E/2F/2G/2|A>B c/2d/2c/2A/2|(3B/2c/2B/2A- A2-|A2- AD/2E/2||\n|:F>D F/2D/2F/2A/2|G/2F/2E/2D/2 CC/2E/2|G>E G/2E/2G/2B/2|A/2G/2F/2E/2 DD/2E/2|\nF>D F/2D/2F/2A/2|G/2F/2E/2D/2 C/2D/2E/2F/2|G/2F/2E/2D/2 C/2D/2E/2F/2|A/2G/2F/2E/2 DD/2E/2|\nF>D F/2D/2F/2A/2|G/2F/2E/2D/2 CC/2E/2|G>E G/2E/2G/2B/2|A/2G/2F/2E/2 DD/2E/2|\nF>D F/2D/2F/2A/2|G/2F/2E/2D/2 C2|GF AG|[M:3/4] EC D2-DD/2E/2:|\n|:A/2G/2F/2E/2 A/2G/2F/2E/2|BA/2F/2 D/2F/2D/2F/2|A/2G/2F/2E/2 A/2G/2F/2E/2|1 DC/2E/2 DD/2F/2:|2 D2-DB/2A/2||\n|:G/2A/2G/2F/2 E/2B/2A/2G/2|F/2G/2F/2E/2 DG/2F/2|E/2F/2E/2D/2 C/2G/2F/2E/2|(3G/2A/2G/2F- FB/2A/2|\nG/2A/2G/2F/2 E/2B/2A/2G/2|F/2G/2F/2E/2 DG/2F/2|E/2F/2E/2D/2 C/2G/2F/2E/2|1 D2- DB/2A/2:|2 D4||"}],"21532":[{"meter":"3/4","mode":"Amajor","abc":"|:ef/2g/2 a2 ag|ed c2 BA|AB BB cc|"},{"meter":"3/4","mode":"Amajor","abc":"[M:6/8]|:c/B|A2a -a>ag|e>dc -c>BA|A>BB B>cc|E3 -E>AG|\nF2a -a>ag|e>dc -c>BA|A>Bc e2A|c2{dc}B -B>dc|\nA2a -a>ag|e>dc -c>BA|A>BB B>cc|E3 -E2E|\nE>FF F>GG|G>AA A>BB|B>ce dcA|-A3 -A3/:|\nA/G|(EF)LF z>AG|(EF)F G>AA|A>BB B>cc|E3 -E>AG|\nF2{GF}E F2{GF}E|FED C>B,A,|{C}D2D E2E|CB,2 -B,>AG|\n(EF)LF z>AG|(EF)F G>AA|A>BB B>cc|E3 -E2E|\nE>FF F>GG|G>AA A>BB|B>ce dcA|-A3 -A3/||"}],"21680":[{"meter":"3/4","mode":"Gmajor","abc":"DG/A/|:B2 Bd BG|E2 D2 GA|B2 Bd GB|"},{"meter":"3/4","mode":"Gmajor","abc":"V:1\nDG/A/|:B2 Bd BG|E2 D2 GA|B2 Bd GB|"},{"meter":"3/4","mode":"Gmajor","abc":"V:1\nDG/A/|:\"G\"B2 Bd BG|\"C\"E2 \"G\"D2 GA|\"G\"B2 Bd GB|"}],"21694":[{"meter":"6/8","mode":"Eminor","abc":"|:c|BEE GEB|EGE edB|ADD FDA|"},{"meter":"6/8","mode":"Adorian","abc":"|:c|BEE GEB|EGE edB|ADD FDA|"}],"21316":[{"meter":"2/4","mode":"Amixolydian","abc":"|:ec BA|c2B2|dc dc|B3c/d/|"},{"meter":"2/4","mode":"Dmajor","abc":"F|:AF ED|F2 E2|GF GF|"},{"meter":"2/4","mode":"Amixolydian","abc":"|:c|ec BA|c2 Bc|dc dc|"}],"21863":[{"meter":"4/4","mode":"Gdorian","abc":"|:G3d cAFA|GdcA f2A/G/F|G3d cAFA|"},{"meter":"4/4","mode":"Edorian","abc":"|:E3B AFDF|EBAF d2F/2E/2D|E3B AFDF|"}],"21070":[{"meter":"3/4","mode":"Dminor","abc":"|:A ^cd|e2 Ae eg|f2-fe fg|d2 de (3fed|"},{"meter":"3/4","mode":"Eminor","abc":"|:B ^de|f2 Bf fa|g2-gf ga|e2 ef (3gfe|"}],"21458":[{"meter":"6/8","mode":"Gmajor","abc":"|:e|dBG G2D|GBd e2d|cAA A2G|"},{"meter":"6/8","mode":"Dmajor","abc":"|:B|AFD D2A,|DFA B2A|GEE E2D|"}],"21117":[{"meter":"4/4","mode":"Dmajor","abc":"de|:f2a2 d2cA|BdcB A2Bc|d2cd e2de|"},{"meter":"4/4","mode":"Dmajor","abc":"de|:f2a2 d2cA|BdcB A2Bc|d4 e2de|"},{"meter":"4/4","mode":"Dmajor","abc":"a4|:f2a2 d2cA|BdcB A2Bc|d2cd e2de|"}],"21076":[{"meter":"4/4","mode":"Dmajor","abc":"|:AG|F2EF DFFD|FAAB B2AB|d2fd BddB|"},{"meter":"4/4","mode":"Dmajor","abc":"|:B AG|F2EF DEFD|FAAB B2AB|d2fd BcdB|"}],"21480":[{"meter":"4/4","mode":"Aminor","abc":"|:E|c3 c {c}B2 B2|Ac BA A^G z A/2B/2|c3 c {c}B2 B2|"},{"meter":"4/4","mode":"Bminor","abc":"|:d2 d3/2 d/2 c2 c3/2 c/2|Bd cB ^A F2 z|B2 B3/2 B/2 ^AF z F|"},{"meter":"4/4","mode":"Aminor","abc":"c2 c3/2c/2 cBBB|AcBA ^G E2 z|A2 A3/2A/2 ^G/2E3/2 z E|"},{"meter":"4/4","mode":"Eminor","abc":".g2 .g.g {g}f2 .f.f|egfe ^dB2z|.e2 .e.e ^dB zB|"},{"meter":"4/4","mode":"Aminor","abc":"c2 c3/2c/2 B2 BB|AcBA ^G E2 z|A2 A3/2A/2 ^G E2 E|"}],"21199":[{"meter":"3/4","mode":"Dmajor","abc":"(3ABc|:d3 fed|B2 A3 F|A3 FED|"},{"meter":"3/4","mode":"Dmajor","abc":"(3ABc|:d3 fed|B2 A3 F|A3 FED|"}],"21839":[{"meter":"4/4","mode":"Dmajor","abc":"|:!downbow! A,B,DE \"D\"{E}F2F2|EFED \"G\"G,4|!upbow! EFED \"Bm\" B,2 B,2|"},{"meter":"4/4","mode":"Dmajor","abc":"|:A,B,DE \"D\"F3F|EFED \"G\"G,4|EFED \"Bm\" B,3 B,|"}],"21097":[{"meter":"4/4","mode":"Gmajor","abc":"DGGF GABd|c2 AG FGAF|DGGF GABd|"},{"meter":"4/4","mode":"Gmajor","abc":"|:\"G\"DGGF GABd|\"Am\"c2 AG \"D\"FGAF|\"G\"DGGF GABd|"}],"21261":[{"meter":"3/4","mode":"Aminor","abc":"EG|\"Am\"A6|\"F\"A6|\"C\"c3d ec|"},{"meter":"3/4","mode":"Eminor","abc":"FA|B6|B6|d3e fd|"}],"21679":[{"meter":"6/8","mode":"Dmixolydian","abc":"|:A|d2f edc|d2e dcA|~G3] BAG|"},{"meter":"6/8","mode":"Dmixolydian","abc":"|:A|\"D\"d2f edc|d2e dcA|\"G\"~G3] BAG|"}],"21075":[{"meter":"4/4","mode":"Dmajor","abc":"|:D3 D- D2 DD|A,B,B,/B,/B, B,A,B,D|DEED DEE/E/E|"},{"meter":"4/4","mode":"Dmajor","abc":"|:d3 d- d2 dd|A ~B3 BABd|deed d~e3|"}],"21624":[{"meter":"4/4","mode":"Amixolydian","abc":"|:A2cA aAcA|B2d/c/B gBbB|A2cA aece|1"},{"meter":"4/4","mode":"Amajor","abc":"|:a|A2 c/B/A aecA|B2 d/c/B fBbB|A2 c/B/A aece|"}],"21965":[{"meter":"4/4","mode":"Amixolydian","abc":"|:CEAB cAdc|BGFG EFED|CEAB cdec|"},{"meter":"4/4","mode":"Dmixolydian","abc":"|:FAde fdgf|ecBc ABAG|FAde fgaf|"}],"21576":[{"meter":"4/4","mode":"Gmajor","abc":"dc|:B3G AGFE|DFAF GBdB|cegc Bdgb|"},{"meter":"4/4","mode":"Gmajor","abc":"|:B3G AGFE|DFAF GBdB|cecA BdBG|"},{"meter":"4/4","mode":"Gmajor","abc":"dc|:\"G\" B3G \"C\" AGFE|\"D\" DFAF \"G\" G~B3|\"C\" cegc \"G\" Bdgb|"}],"21184":[{"meter":"4/4","mode":"Gmajor","abc":"D|:G3B dBB2|gBeB dBB2|ceAc BdGB|"},{"meter":"4/4","mode":"Gmajor","abc":"|:G3B dB~B2|gBfB eB~d2|c2Ac BAGB|"}],"21011":[{"meter":"4/4","mode":"Gdorian","abc":"D2|:G3A BABc|d3g dcBc|d3g dcBc|"},{"meter":"4/4","mode":"Edorian","abc":"B2|:E3F GFGA|B3e BAGA|B3e BAGA|"}],"21276":[{"meter":"4/4","mode":"Fmajor","abc":"|:c4 c3 d|fdcB cBGB|F4 ~F3G|"},{"meter":"4/4","mode":"Amajor","abc":"|:e4 e3 f|afed edBd|~A3A ~A3B|"}],"21956":[{"meter":"4/4","mode":"Dmajor","abc":"ee|e2 e2 B2 c2|d3 c B2 ee|e2 e2 B2 c2|"},{"meter":"4/4","mode":"Dmajor","abc":"d|:e2 e2 B2 c2|d3 c B2 dd|e2 e2 B2 c2|"}],"21189":[{"meter":"4/4","mode":"Eminor","abc":"ef|g2 gf/e/ ^d2ef|{d}B2^c^d e2- e=d/=c/|{d}B2{d}BA/G/ F2GA|{B}BA GF E Bef|\ng2 gf/e/ ^d2ef|B^c-^c^d e2 e=d/=c/|B2 BA/G/ JF3G|{B}G6|\nef|{a}g2 gf/e/ ^d2ef|B^c-{d}^c^d e2- e=d/=c/|B2BA/G/ F2GA|{B}BA GF E Bef|\ng2 {a}gf/e/ ^d2ef|B^c-^c^d e2 e=d/=c/|{d}B2 BA/G/ TF3G|{B}G6|\n{c}BG|d2Ac B~g2d|e2Bd c2BA|^G2AB c{G}cBA|{d}A4-A2dA|\n{c}B~g2d e2Bd|^ceae ~f2^ce|dd^cB ^A3 B|B4-B fbf|\n~^g2fe a2e=g|~f2ed g2d=f|e~a2e f2^ce|^d2B2 B2 eB|\nc2 dA B2cG|A2BF G2 FE|^D2EF ~G2 FE|E6|"},{"meter":"4/4","mode":"Eminor","abc":"V:1\nef|:g2 fe ^d2ef|B2^c^d e2=d=c|B2AG F2GA|BA GF E2 ef|\ng2 fe ^d2ef|B2^c^d e2=d=c|B2 AG \"tr\"F3G|1 G6 ef:|2 G6 BG||\n|:d2Ac B2gd|e2Bd c2BA|^G2AB c2BA|A6dA|\nB2gd e2Bd|c2ae f2^ce|d2^cB \"tr\"^A3 B|B6 bf|\n^g2fe a2e=g|f2ed g2d=f|e2ae f2^ce|^d2B4 eB|\nc2 dA B2cG|A2BF G2 FE|^D2EF G2 FE|1 E6 BG:|2 E6||\nV:2\nGF|:E2A2B2A2|G2F2E2F2|G2A2B2A2|G2B2 EFGF|\nE2A2B2A2|G2F2E2F2|G2c2d2D2|1 G6 GF:|2 G6G2||\n|:F2D2G2B2|c2^G2A2d2|e2A2e2E2|ABAGF2D2|\nG2B2c2^E2|A2c2d2^A2|B2e2f2F2|B^AB^c^d2B2|\ne2=d2^c2=A2|d2=c2B2G2|c2B2A2F2|B3c BA^G2|\nAef2 =G^de2|F^c^d2 E2A2|B2A2B2B,2|1 E6 G2:|2 E6||\nV:3\n[K:clef=bass]G,F,|:E,2A,2B,2A,2|G,2F,2E,2F,2|G,2A,2B,2A,2|G,2B,2 E,F,G,F,|\nE,2A,2B,2A,2|G,2F,2E,2F,2|G,2C2D2D,2|1 G,6 G,F,:|2 G,6G,2||\n|:F,2D,2G,2B,2|C2^G,2A,2D2|E2A,2E2E,2|A,B,A,G,F,2D,2|\nG,2B,2C2^E,2|A,2C2D2^A,2|B,2E2F2F,2|B,^A,B,^C^D2B,2|\nE2=D2^C2=A,2|D2=C2B,2G,2|C2B,2A,2F,2|B,3C B,A,^G,2|\nA,EF2 =G,^DE2|F,^C^D2 E,2A,2|B,2A,2B,2B,,2|1 E,6 G,2:|2 E,6||"}],"21944":[{"meter":"4/4","mode":"Emajor","abc":"[EB]2|[Ac]2(AB cde2)|(GBe2) (ede2)|FGAB cAB2|(AGFG) E2ge|\nfd(Bc def)a|ge(Bd efg)b|!p!fd(Bc def)a|ge(Bd efg)b|\n!f!(edcd) (edcB)|(^AGFG ABcd)|!p!(edcd) (edcB)|(^AGFG ABce)|\n!f!(dcB)c def=A|GBed (e^ab)c|(EdcB) (FcB^A)|BFDF B,2:|\n[Bf]2|[eg]2(ef g^ab2)|(dfb2) (b^ab2)|ce=ac ^bdgf|(fede) c2ec|\n(GABc =d)gbd|(cBAB c)eac|!p!(GABc =d)gbd|(cBAB c)eac|\n!f!=dBGF (^EGB)d|cAF=E (=DCD)c|(Bagf) (cgf^e)|fcAc F2af|\ndf(Bc def)a|gb(ef gab)=d|ceAc (fga)f|(edc)d B2[EB]2|\n[Ac]2(AB cdef)|dfaf (dB)(cA)|Geb2 (agfg) & x4 B2x2|eBGB E2||"},{"meter":"4/4","mode":"Cmajor","abc":"[G2C2]|[A2F2]FG AB c2|EG c2 cB c2|DE FG AF G2|"},{"meter":"4/4","mode":"Dmajor","abc":"|[A2D2]|[B2G2]GA Bc d2|FA d2 dc d2|EF GA BG A2|"}],"21385":[{"meter":"6/8","mode":"Eminor","abc":"|:B,2E EDB,|GAB EDB,|BGG dGG|"},{"meter":"6/8","mode":"Eminor","abc":"|:B,2E EDe,|GAB EDB,|BGG dGG|"}],"21849":[{"meter":"4/4","mode":"Emajor","abc":"|:\"EI\" B2eB cege|BeeB AFFE|GBAc Bcef|"},{"meter":"4/4","mode":"Dmajor","abc":"|:A2dA Bdfd|AddA GEED|FAGB ABde|"}],"21030":[{"meter":"3/4","mode":"Cmajor","abc":"ED C2 CD|EF G2 E2-|E G A2 GE|"},{"meter":"3/4","mode":"Cmajor","abc":"ED|C2 CD EF|G2 E3 G|A2 GE DE|"},{"meter":"3/4","mode":"Gmajor","abc":"BA G2 GA|Bc d2 B2-|B d e2 dB|"}],"21870":[{"meter":"6/8","mode":"Dmajor","abc":"|:B2 A AAA|B2 G GGG|B2 A AAA|"},{"meter":"6/8","mode":"Adorian","abc":"|:B2A AAA|B2G GGG|B2A AAA|"}],"21665":[{"meter":"6/8","mode":"Emajor","abc":"|:EFE gfe|cAc e2f|ecB beg|"},{"meter":"6/8","mode":"Emajor","abc":"|:EFE gfe|cAc [e2e2]f|ecB beg|"}],"21875":[{"meter":"4/4","mode":"Amajor","abc":"c2 c/d/c/B/ Ac Ec/d/|ee f/e/c e2 ef/g/|a2 ga fe cA|"},{"meter":"4/4","mode":"Gmajor","abc":"\"G\"B4 BcBA|G2B2 D2Bc|d2d2 edB2|"}],"21923":[{"meter":"6/8","mode":"Cmajor","abc":"|:Gcc cBc|Gcc e3|Gcc cBc|"},{"meter":"6/8","mode":"Dmajor","abc":"|:Add dcd|Add f3|Add dcd|"}],"21581":[{"meter":"3/4","mode":"Dmajor","abc":"gf|e2d2 ef|g4 fg|.a2 fagf|"},{"meter":"3/4","mode":"Dmajor","abc":"GF|E2D2 TEF|G4 FG|A2 FAGF|"}],"21315":[{"meter":"9/8","mode":"Fmajor","abc":"|:D|C2c AGF FGF|D2F GAc cdc|fcd fdc AGF|"},{"meter":"9/8","mode":"Gmajor","abc":"|:E|D2d BAG GAG|E2G ABd ded|gde ged BAG|"}],"21517":[{"meter":"4/4","mode":"Dmixolydian","abc":"|:AcBG A2FD|AcBG c2ge|decA BGGA|"},{"meter":"4/4","mode":"Dmixolydian","abc":"|:\"D\"AcBG A2FD|AcBG \"A\"~c2ge|\"D\"decA \"G\"BGGA|"}],"21050":[{"meter":"4/4","mode":"Dmajor","abc":"fe|:dfaf dfBg|fAde fdBe|GBdg fedf|"},{"meter":"4/4","mode":"Dmajor","abc":"|:fe|dfaf dfBg|fede fdAF|GBdg fedf|"}],"21503":[{"meter":"4/4","mode":"Fmajor","abc":"|:F3 A f2 dA|cdBA Bddd|F3 A f2 dA|"},{"meter":"4/4","mode":"Gmajor","abc":"|:G3 B g2 eB|decB ceee|G3 B g2 eB|"}],"21049":[{"meter":"3/4","mode":"Dmajor","abc":"cdc|:B3 cdc|B3 cde|f2 fedc|"},{"meter":"3/4","mode":"Dmajor","abc":"dc|:B3 d dc|B2 Bc de|f2 fe dc|"}],"21437":[{"meter":"6/8","mode":"Edorian","abc":"|:A|Bee dBB|AFA B2A|Bee dBB|"},{"meter":"6/8","mode":"Aminor","abc":"|:GGE AAE|GcB AAE|GGE AAE|"},{"meter":"6/8","mode":"Bminor","abc":"|:AAF BBF|Adc BBF|AAF BBF|"}],"21286":[{"meter":"4/4","mode":"Gmajor","abc":"|:z d|DG G/G/G Bc d2|bgaf gedg|e/f/g dB cBAd|"},{"meter":"4/4","mode":"Gmajor","abc":"|:GE|DG G/F/G Bd d/^c/d|bgaf gedg|e/g/e dB cBAc|"}],"21447":[{"meter":"9/8","mode":"Gminor","abc":"|:B/2A/2|G3 DGA BAG|F3 CFA cBA|G2 G DGA BdB|"},{"meter":"9/8","mode":"Bminor","abc":"|:d/2c/2|B3 FBc dcB|A3 EAc edc|B2 B FBc dfd|"}],"21464":[{"meter":"4/4","mode":"Amajor","abc":"|:E3 F A2 cd|edcA dcAE|D2 FAAG E2|"},{"meter":"4/4","mode":"Dmajor","abc":"|:A3 B d2 fg|agfd gfdA|G2 Bddc A2|"}],"21647":[{"meter":"3/2","mode":"Gmajor","abc":"L:1/4\nM:6/4\nBcd dB/c/d/B/|dg2 B2G|Bc d dB/c/d/B/|Af2 A2e|"},{"meter":"3/2","mode":"Gmajor","abc":"[M:6/4]|:G2|B3cd2 d2BcdB|d2g4 B4G2|B3cd2 d2BcdB|"}],"21200":[{"meter":"4/4","mode":"Amajor","abc":"A3B cBAE|~F3E ~A3E|~F3E ~A3B|"},{"meter":"4/4","mode":"Amajor","abc":"A3B cBAE|~F3E ~A3E|~F3E ~A3B|"}],"21254":[{"meter":"6/8","mode":"Cmajor","abc":"|:E3 FGA|G3 G,CD|E3 cGE|"},{"meter":"6/8","mode":"Cmajor","abc":"|:EDE FGA|G3 GcD|E3 cGE|"}],"21371":[{"meter":"4/4","mode":"Gmajor","abc":"|:D|GAGF TE2D2|{B}dedc B2AB/A/|GDGA B2ge/c/|"},{"meter":"4/4","mode":"Gmajor","abc":"|:DE/F/ | GAGF E2 D2 | dd g/f/e/d/ B2 c/B/A/G/ | GFGA B2 g/f/e/d/ |"}],"21288":[{"meter":"4/4","mode":"Cdorian","abc":"|:B,|G,2CG, B,CC/C/C|ECEF ECB,F,|G,B, CG, B,CC/C/C|"},{"meter":"4/4","mode":"Aminor","abc":"|:G|E2AE GAA/A/A|cAcd cAGD|EG AE GAA/A/A|"}],"21771":[{"meter":"4/4","mode":"Eminor","abc":"|:EBAB2AG A-|AAGED2E2|EedB A2BE-|"},{"meter":"4/4","mode":"Eminor","abc":"|:EBAB BAGA|~A2GED2E2|EedB A2BE-|"}],"21465":[{"meter":"6/8","mode":"Cmajor","abc":"Gcc ecc|dcd ecA|Gcc ecc|"},{"meter":"6/8","mode":"Amajor","abc":"|:EAA cAA|BAB cAF|EAA cAA|"},{"meter":"6/8","mode":"Dmajor","abc":"|:Add fdd|ede fdB|Add fdd|"}],"21389":[{"meter":"4/4","mode":"Dmajor","abc":"|:dB|A2 d2 fded|f2 f2 edBd|A2 d2 fded|"},{"meter":"4/4","mode":"Dmajor","abc":"dB|:\"D\"A2d2 fded|f2f2 edBd|A2d2 fded|["}],"21994":[{"meter":"6/8","mode":"Dmajor","abc":"|:D2E F2G|A2d d2d|c2B A2B|"},{"meter":"6/8","mode":"Dmajor","abc":"M:12/8\n|:D3 EFG A2d d2z|=c2B A2B c2A GFE|D3 EFG A2d d2f|"}],"21406":[{"meter":"4/4","mode":"Emajor","abc":"|:E2 G2|B3 G B2 c2|B4 G2 B2|g3 f e2 c2|"},{"meter":"4/4","mode":"Dmajor","abc":"DF|:\"D\"AF AB A2FA|fe dB A2Fd|\"A\"cE EF GF GB|"}],"21433":[{"meter":"4/4","mode":"Dmajor","abc":"B3cdef^g|a4b2fd|{f}e3d B2G2|"},{"meter":"4/4","mode":"Gminor","abc":"GA B/c/d/=e/|f2 gd/B/|{d}cB GE|F2 D=E/^F/|"}],"21949":[{"meter":"4/4","mode":"Gdorian","abc":"|:dg{a}gf g3d|gfga e2c2-|cdfg d2B2-|"},{"meter":"4/4","mode":"Edorian","abc":"|:Beed e3B|edef c2A2-|ABde B2G2-|"}],"21009":[{"meter":"6/8","mode":"Bmixolydian","abc":"K:B\n|:B,DF B2B|c2f dcB|EGe dcB|"},{"meter":"6/8","mode":"Dmajor","abc":"|:DFA d2d|e2a fed|GBg fed|"}],"21013":[{"meter":"4/4","mode":"Gminor","abc":"|:{B}c3 A G2 C2|E5 BB|d3 B E4|"},{"meter":"4/4","mode":"Bminor","abc":"|:{d}e3 c B2 E2|G5 dd|f3 d G4|"},{"meter":"4/4","mode":"Cdorian","abc":"[M:3/2][L:1/4]c A|:G C E3 B/B/|d d/B/ E3 E/D/|c F F E E/F/ (3F/E/C/|"},{"meter":"4/4","mode":"Edorian","abc":"[M:3/2][L:1/4]e c|:B E G3 d/d/|f f/d/ G3 G/F/|e A A G G/A/ (3A/G/E/|"}],"21564":[{"meter":"4/4","mode":"Amajor","abc":"E|A2AA AGFE|EAAB AGFE|A2AA Acec|"},{"meter":"4/4","mode":"Dmajor","abc":"A|d2dd dcBA|Adde dcBA|d2dd dfaf|"}],"21021":[{"meter":"3/4","mode":"Fmajor","abc":"M: 5/4\n|:A3c3 G2A2|F3EDC DEFG|c4G2 c2G2|"},{"meter":"3/4","mode":"Dmajor","abc":"L:1/8\nM:5/4\nK:D\n|:\"D\" f3 a3 e2 f2 |\"Bm\" d3 cBA Bcde |\"A\" a3 e3 a2 e2 |"}],"21522":[{"meter":"4/4","mode":"Adorian","abc":"|:GAAG AcBG|~d2 cA d2 cA|GAAG AcBG|"},{"meter":"4/4","mode":"Edorian","abc":"|:deed egfd|~a2 ge a2 ge|deed egfd|"}],"21648":[{"meter":"6/8","mode":"Dmajor","abc":"|:DFA d2D|c2D BAF|E3 GAB|"},{"meter":"6/8","mode":"Dmajor","abc":"|:DFA {c}d2D|{cd}c2D {Bc}BAF|~E3 GAB|"}],"21105":[{"meter":"4/4","mode":"Amajor","abc":"|:ecdB cABG|E2 DE B,CDF|EAcA dBcd|"},{"meter":"4/4","mode":"Amajor","abc":"|:\"A\"ecdB cABG|\"E\"E2 DE B,CDF|\"A\"EAcA \"Bm\"dBcd|"}],"21701":[{"meter":"4/4","mode":"Dmajor","abc":"|:dA (3AAA defd|eB (3BBB efge|fa (3aaa afdf|"},{"meter":"4/4","mode":"Dmajor","abc":"|:dA A/A/A defd|eB B/B/B efge|fa a/a/a afdf|"},{"meter":"4/4","mode":"Dmajor","abc":"|:dA A/A/A defd|eB B/B/B efge|faag agec|"}],"21067":[{"meter":"4/4","mode":"Eminor","abc":"|:A,|B,EED EFGA|BE (3EDE B,EGE|D2 ^CE DEFG|"},{"meter":"4/4","mode":"Eminor","abc":"|:D|B,E{F}ED EFGA|BE (3E/E/E/E B,EGE|D/E/D ^CE DEFG|"}],"21540":[{"meter":"3/4","mode":"Gmajor","abc":"G G/F/E|:\"G\"D2 DE GA|\"G\"Bg2g gf|\"C\"e3g ed|"},{"meter":"3/4","mode":"Gmajor","abc":"G G/F/E|:\"G\"D2 DE GA|\"G\"Bg2g gf|\"C\"e3g ed|"}],"21223":[{"meter":"6/8","mode":"Gmajor","abc":"|:DGA|BAB cBA|BGE DGB|dcB cBA|"},{"meter":"6/8","mode":"Gmajor","abc":"|:DGA|BAB cBA|BGE DGB|dcB cBA|"},{"meter":"6/8","mode":"Gmajor","abc":"|:DGA BAB | cBA BGE | DGB dcB |"}],"21907":[{"meter":"4/4","mode":"Dmajor","abc":"AA|\"D\" A2 A2 d e2 f|f6 z f|\"G\" g3 g g2 a2|"},{"meter":"4/4","mode":"Gmajor","abc":"DD|\"G\" D2 D2 G A2 B|B6 z B|\"C\" c3 B c2 d2|"}],"21177":[{"meter":"4/4","mode":"Adorian","abc":"|:d|e2dB ABcd|eaag efge|dGG2 EGDG|"},{"meter":"4/4","mode":"Dmajor","abc":"|:FG|Adfe dBAF|G2 ED E2 EF|GBef gBed|"}],"21289":[{"meter":"4/4","mode":"Amajor","abc":"|:A-B|c2 A2 e2 A2|a2 f2 d2 A-B|cAeA fecA|"},{"meter":"4/4","mode":"Amajor","abc":"|:AB|c2 A2 e2 A2|a2 f2 d2 AB|cAeA fecA|"}],"21678":[{"meter":"4/4","mode":"Bminor","abc":"|:B2 B2 BABc|B2 G2 E2 FG|F2 G2 A2 Bc|"},{"meter":"4/4","mode":"Aminor","abc":"|:A2 A2 AGAB|A2 F2 D2 EF|E2 F2 G2 AB|"}],"21505":[{"meter":"6/8","mode":"Cmajor","abc":"|:G2c cdc|BGA Bcd|efg abc'|"},{"meter":"6/8","mode":"Gmajor","abc":"D2G GAG|FDE FGA|Bcd efg|"}],"21042":[{"meter":"4/4","mode":"Eminor","abc":"|:BE~E2 GEDE|GABG A2 B/c/d|e2Be deBG|"},{"meter":"4/4","mode":"Dminor","abc":"|:D3 A FD D2|FGAF G2 (3ABc| d2 Ad dcAF|"}],"21163":[{"meter":"4/4","mode":"Gmajor","abc":"|:D|G2 BG E2 AG|FDEF GFED|G2 BG E2 AG|"},{"meter":"4/4","mode":"Gmajor","abc":"(3DEF|G2 BG E2 AG|FDEF GFED|G2 BG E2 AG|"}],"21171":[{"meter":"2/4","mode":"Gmajor","abc":"|:DB BB|cE EG|FA DF/G/|GB d2|"},{"meter":"2/4","mode":"Dmajor","abc":"|:fz fe|ed de|ef fa|ag g2|"}],"21212":[{"meter":"6/8","mode":"Gminor","abc":"|:G,A,G, B,G,C|DFD G2A|BAG FDC|"},{"meter":"6/8","mode":"Gminor","abc":"|:CDC ECF|GBG c2d|edc BGF|"}],"21244":[{"meter":"4/4","mode":"Gmajor","abc":"A|:BGGF GABc|dG A/G/F GFDE|=F/G/F E/F/G FGAB|"},{"meter":"4/4","mode":"Gmajor","abc":"A|:BGGF GABc|dGAF GFDE|=F2EG =FGAB|"},{"meter":"4/4","mode":"Amajor","abc":"|:cA{B}AG ABcd|eA{B}AB {B}A=GEF|~=G2 F/G/A GAB=c|"}],"21929":[{"meter":"9/8","mode":"Gminor","abc":"|:B2d cBc dBG|B2d cBc dBF|A2c A2c AGF|"},{"meter":"9/8","mode":"Adorian","abc":"|:c2e dcd ecA|c2e dcd ecG|B2d B2d BAG|"}],"21307":[{"meter":"3/2","mode":"Eminor","abc":"|:EFGB A2GA BGFG|EFGB A2GA BGE2:||:c2 Ac BAGF EFGB|"},{"meter":"3/2","mode":"Eminor","abc":"M:3/4\n|:EF GB A2|GA BG FG|EF GB A2|GA BG E2:|"},{"meter":"3/2","mode":"Eminor","abc":"EF GB A2 GA BG ED|EF GB (3ABA GA BG ED|EF GB (3ABA GA BG ED|"}],"21932":[{"meter":"3/4","mode":"Amajor","abc":"V:1\n|:\"A\"e2 A \"E7\"BAG|\"A\"A3 E3|\"D\" FAd fed|"},{"meter":"3/4","mode":"Amajor","abc":"|:\"A\"e2 A \"E7\"BAG|\"A\"A3 E3|\"D\" FAd fed|"}],"21683":[{"meter":"6/8","mode":"Dmajor","abc":"|:\"D\"dec dcA|GAE E/E/FD|d2c dfa|"},{"meter":"6/8","mode":"Dmajor","abc":"|:dec dcA|GAE EFD|dec df/g/a|"}],"21661":[{"meter":"4/4","mode":"Dmajor","abc":"D2DF A2AB|deed efdB|D2DF AFAB|"},{"meter":"4/4","mode":"Dmajor","abc":"D3F A3B|deed efdA|DGDF AFAB|"}],"21279":[{"meter":"4/4","mode":"Amixolydian","abc":"e|fecA EAcA|dBGB FBdB|cAEA ceaf|"},{"meter":"4/4","mode":"Amajor","abc":"e|fecA EAcA|dBGB FBdB|cAEA ceaf|"}],"21496":[{"meter":"3/4","mode":"Dminor","abc":"[D2A2][D2A2] de|f2.A2.A2|f2 gfed|"},{"meter":"3/4","mode":"Gminor","abc":".d2.d2 ga|b2d2 .d2|.b2 c'bag|"},{"meter":"3/4","mode":"Dminor","abc":"F3/2G/2|A2 A2 de|f2 A2 A2|f2 gf ed|"},{"meter":"3/4","mode":"Eminor","abc":"|:B2B2ef|g2B2B2|g2ag fe|"}],"21622":[{"meter":"3/4","mode":"Fmajor","abc":"|:FD|CD F2F z|F4 F2|G2 F/4G/2A A/4G/2F|"},{"meter":"3/4","mode":"Fmajor","abc":"|:FG/A/|B2B2B2|A2A2A2|FA/c/ BA GF|"},{"meter":"3/4","mode":"Gmajor","abc":"|:GA/B/|c2c2c2|B2B2B2|GB/d/ cB AG|"},{"meter":"3/4","mode":"Dmajor","abc":"AA|B2d2.d2|.d4 .f.f|efafed|"},{"meter":"3/4","mode":"Fmajor","abc":"CC|D2 F2 F2|F4 AA|GA cA GF|"}],"21499":[{"meter":"3/4","mode":"Aminor","abc":"M:5/4\n|:Ec cB AG/F/ ED/E/ FD|EA/B/ cB/A/ EA cB B2|Ec cB AG/F/ ED/E/ FD|"},{"meter":"3/4","mode":"Bminor","abc":"M:5/4\n|:Fd dc BA/G/ FE/F/ GE|FB/c/ dc/B/ FB dc c2|Fd dc BA/G/ FE/F/ GE|"},{"meter":"3/4","mode":"Aminor","abc":"M: 2/4\n|:E2c2 | c2B2 | A2 GF | E2DE |"},{"meter":"3/4","mode":"Bminor","abc":"M:2/4\n|:Fd dc|BA/G/ FE/F/|GE FB/c/ |dc/B/ FB|"},{"meter":"3/4","mode":"Aminor","abc":"|:\"Am\"Ec cB|AG/F/ ED/E/|\"Dm\"FD \"Am\"EA/B/ |cB/A/ EA|\"E7\"cB B2|\n\"Am\"Ec cB|AG/F/ ED/E/|\"Dm\"FD \"Am\"EA/B/ |\"F\"cB/A/ \"Esus4\"EA|\"Am\"BA A2:|\n|:\"Am\"Ae ed/e/|\"Dm\"fd \"Am\"ed/c/|\"Bdim\"Bd \"Am\"cB/A/|\"G\"Bc \"F\"d/c/B/A/|\"E7\"cB B2|\n\"Am\"Ae ed/e/|\"Dm\"fd \"Am\"ed/c/|\"Bdim\"Bd \"Am\"cB/A/|\" Fmaj7(#11) \"BA/G/ EA|\"Am\"BA A2:|"}],"21481":[{"meter":"4/4","mode":"Amixolydian","abc":"M:2/2\n|:B2B2c2c2-|ceec A2cA|BddB G2B2|"},{"meter":"4/4","mode":"Amixolydian","abc":"|:\"A\"E3/4F//E/D/ E3/2F/ E2 E2|A3/2B/ cB B3/2A/ A3/2B/|c2 c3/2B/ \"G\"=G2 G2-|"}],"21179":[{"meter":"3/4","mode":"Eminor","abc":"|:G3 A FG|E2 EG Be|cBAG FG|"},{"meter":"3/4","mode":"Eminor","abc":"EF|:G3A FG|E2 EGBe|cBAG FG|"}],"21144":[{"meter":"4/4","mode":"Fmajor","abc":"|:\"F\"F3G ABcA|\"Bb\"BdcB \"F\"cf\"C\"eg|\"F\"f2cB \"Dm\"ABcF|"},{"meter":"4/4","mode":"Gmajor","abc":"|:\"G\"G3A BcdB|\"C\"cedc \"G\"dg\"D\"fa|\"G\"g2dc \"Em\"BcdG|"}],"21065":[{"meter":"4/4","mode":"Amajor","abc":"|:EFce c2 Bc|effe c2 BA|ABBc BAFd-|"},{"meter":"4/4","mode":"Eminor","abc":"|:DEBd B2 AB|deed B2 AG|GAAB AGEc-|"}],"21413":[{"meter":"4/4","mode":"Fmajor","abc":"|:fe|f2 c=B c2 AF|AB AG F2 fe|f2 c=B c2 AF|"},{"meter":"4/4","mode":"Dmajor","abc":"|:dc|d2 A^G A2 FD|FG FE D2 dc|d2 A^G A2 FD|"},{"meter":"4/4","mode":"Gmajor","abc":"|:gf|g2 d^c d2 BG|Bc BA G2 gf|g2 d^c d2 BG|"}],"21297":[{"meter":"12/8","mode":"Adorian","abc":"|:a2a a2g e2d ede|gag g2e d2B G2B|A2B c2d ede a2g|1"},{"meter":"12/8","mode":"Adorian","abc":"M: 2/4\n|:ab ag ed ef|ga ge d/B/d G2|AB cd ee eB/d/|1 ee dB A2 A2:|2"}],"21599":[{"meter":"6/8","mode":"Dmajor","abc":"A|Ad.d dcd|ge.d czd/e/|fa.f ge.f|"},{"meter":"6/8","mode":"Amajor","abc":"E|(EA).A .A.G.A|(dB).A GAB|(c/d/e).c .d.B.c|A>BA A2E|\nEAA AGA|dBA GAB|(c/d/e).c .d.B.c|.A>.B.A .A2||A|\n.A.=g.g .g2a|(=ge).e (dB).B|.A.a.a (a=g).a|(b=g).e !fermata!e3 d/c/|\n.d.e.f =.g.a.g|.f.d.c .B.c.d|e2 ^d (e/f/=g).e|(e/d/).B.A .A2A|\nA=gg g2a|=gee dBB|Aaa a=ga|b=ge !fermata!e2 d/c/|\n.d.e.f =.g.a.g|.f.d.c .B.c.d|!fermata![c2e2]^d (e/f/=g).e|.d.B.A [C3E3A3]||"},{"meter":"6/8","mode":"Gmajor","abc":"|:D|DGG GFG|cAG F2 G/A/|BdB cAB|"}],"21880":[{"meter":"3/4","mode":"Eminor","abc":"|:E|:\"E\" F3 BAB|GFE \"D\" F3|BAB \"C\" GFE|"},{"meter":"3/4","mode":"Eminor","abc":"|:E |F3 BAB|GFE F3|BAB GFE|"}],"21610":[{"meter":"6/8","mode":"Gmajor","abc":"D|GAG GFG|ABA A2 G/A/|BcB BAG|"},{"meter":"6/8","mode":"Amajor","abc":"|:.e|ab.a ag.a|bc'.b b2 a/b/|c'd'.c' c'b.a|"}],"21055":[{"meter":"6/8","mode":"Aminor","abc":"|:A,AA cde|{^F}GGG EAD|~A3 cde|"},{"meter":"6/8","mode":"Aminor","abc":"|:A3 cde|G3 EGD|~A3 cde|"},{"meter":"6/8","mode":"Aminor","abc":"[A3E33A,] {B}cde|[G3G,3] EGD|[A3E3A,3] cde|age g2a|\n A3 {B}cde|{F}G3 EGD|age (3def e|1 dcA A2 E:|2 dcA A2 B|\n [cF]FF c{c}de|[dG]GG {c}BAG|A2a {a}ged|efe e2 d|\n [1 [cF]FF c{c}de|[dG]GG {c}BAG|[A2D]A (3Bcd e|dcA A (32GAB:|\n [2 [cF]FF c{c}de|[dG]GG deg|age (3age d|edc dcB||"}],"21489":[{"meter":"6/8","mode":"Gmajor","abc":"|:DGF GBc|BGD CDB,-|B,CD EDE|"},{"meter":"6/8","mode":"Gmajor","abc":"|:\"G\"DGF GBc|BGD CG,\"Bm\"B,-|B,CD EDE|"}],"21084":[{"meter":"6/8","mode":"Dmajor","abc":"|:A|dcd ecA|dcd dcd|afd ecA|"},{"meter":"6/8","mode":"Dmajor","abc":"|:A|dcd ecA|dcd dcd|afd ecA|"},{"meter":"6/8","mode":"Dmajor","abc":"M:9/8\n|:A|dcd ecA dcd|dcd afd ecA|[1 fdB GAB GAB|"}],"21260":[{"meter":"2/4","mode":"Gmajor","abc":"g2 f|:e2 A2|A2 fe|ed BA|"},{"meter":"2/4","mode":"Gmajor","abc":"gf|:e2 A2|e2 fe|ed BA|"}],"21525":[{"meter":"4/4","mode":"Eminor","abc":"|:BEED E2DE|GABG A2GA|BEED E2DE|"},{"meter":"4/4","mode":"Eminor","abc":"BEED E2DE|GABG A2Bd|BEED E2DE|"}],"21274":[{"meter":"3/4","mode":"Amixolydian","abc":"|:A2|A2 cB AG|A2 cd e2|e2 gf ed|"},{"meter":"3/4","mode":"Amixolydian","abc":"|:A2 cB AG | A2 cd e2 | e2 gf ed |"}],"21095":[{"meter":"4/4","mode":"Amajor","abc":"|:\"A\"e2dB cA (3AGA|\"A\"cAdB cABG|\"E\"E3F GFGA|1"},{"meter":"4/4","mode":"Gmajor","abc":"|:\"G\"d2cA BG (3GFG|\"G\"BGcA BGAF|\"D\"D3E FEFG|1"}],"21819":[{"meter":"4/4","mode":"Fmajor","abc":"|:dG~G2 dcAc|dcBA GBAG|AF~F2cF|"},{"meter":"4/4","mode":"Dmajor","abc":"|:BE~E2BAFA|BAGF EGFE|FD~F2 AD~D2|"}],"21828":[{"meter":"4/4","mode":"Dmajor","abc":"|:D2FD ADFA|dfed BAFE|D2FD ADFA|"},{"meter":"4/4","mode":"Dmajor","abc":"A2 Bc|dcdf e/f/e dB|ADFE DEFA|dcdf e/f/e dB|"},{"meter":"4/4","mode":"Dmajor","abc":"|:D2 F/E/D ADFA|dAFA {c}BAFE|DEDF ABAF|"}],"21638":[{"meter":"4/4","mode":"Dminor","abc":"|:DFF/F/D FAA/A/A|{F}GFAG FDCA,|DA,FD FAA/A/A|"},{"meter":"4/4","mode":"Bminor","abc":"|:Bdd/d/B dff/f/f|{d}edfe dBAF|BFdB dff/f/f|"}],"21281":[{"meter":"4/4","mode":"Gmajor","abc":"|:G,2 B,D G2 BG|AGEG Bd d2|G,A,B,D GABG|"},{"meter":"4/4","mode":"Gmajor","abc":"|:G,2B,D G2BG|AGEG Bdd2|G,A,B,D G2BG|"}],"21948":[{"meter":"9/8","mode":"Ddorian","abc":"|:D2A A2G ABc|D2A A2G E2G|D2A A2G ABc|"},{"meter":"9/8","mode":"Ddorian","abc":"|:D2A {_B}A2G A=Bc | D2A {_B}A2G EAE | D2A {_B}A2G A=Bc |"}],"21498":[{"meter":"3/4","mode":"Dmajor","abc":"|:A dc|B3e AG|A3A gf|e3A ea|"},{"meter":"3/4","mode":"Dmajor","abc":"|:A \"D/F#\"dc|\"G\"B3e \"A\"AG|\"D\"A3A \"Em\"gf|\"A\"e3A \"A/C#\"ea|"}],"21173":[{"meter":"4/4","mode":"Fmajor","abc":"|:\"F\"c2FG \"Dm\"ABcF|\"Gm\"Bdgf \"C\"ecBG|\"F\"c2BG Acfc|"},{"meter":"4/4","mode":"Gmajor","abc":"|:\"G\"d2GA \"Em\"BcdG|\"Am\"ceag \"D\"fdcA|\"G\"d2cA Bdgd|"}],"21473":[{"meter":"4/4","mode":"Fmajor","abc":"FG|A2 BA G2 AG|F2ff f2 c/d/f|ga/b/ ag fedc|"},{"meter":"4/4","mode":"Fmajor","abc":"FG|A2 BA G2 AG|F2 ff f2 c/d/f|g/a/b ag {f/g/}fe {d/e/}dc|"},{"meter":"4/4","mode":"Dmajor","abc":"|:DE|F2 GF E2 FE|D2 d2 d2 f2|e2 fe dc BA|"},{"meter":"4/4","mode":"Amajor","abc":"AB|.c2 dc .B2 cB|A2 aa a2 ef/g/|ad'c'b ag{g}fe|"},{"meter":"4/4","mode":"Gmajor","abc":"GA|B2 cB A2 BA|G2 gg g2 d/e/g|a/b/c' ba {g/a/}gf {e/f/}ed|"}],"21776":[{"meter":"3/4","mode":"Cmajor","abc":"EF|:\"C\" G2c2d2|\"Am\" c4 cd|\"F\" e2f2e2|"},{"meter":"3/4","mode":"Gmajor","abc":"B,C|DG- G3A|GF-F2GA|Bc-c2B2|"},{"meter":"3/4","mode":"Gmajor","abc":"B,C|:DG- G3A|GF-F2GA|Bc-c2B2|"},{"meter":"3/4","mode":"Dmajor","abc":"FG|:\"D\" A2d2e2|\"Bm\" d4 de|\"G\" f2g2f2|"}],"21553":[{"meter":"3/4","mode":"Eminor","abc":"B^d|e2 ef ge|d2B2 GA/B/|c2c2 BA|"},{"meter":"3/4","mode":"Aminor","abc":"e2|a2 .abc'a|g2e z cd/e/-|f2 f2 ed|"},{"meter":"3/4","mode":"Eminor","abc":"B2|e2 .efge|d2B z GA/B/-|c2 c2 BA|"},{"meter":"3/4","mode":"Dminor","abc":"A^c|d3 efd|c2 A2 FA|B3 BAG|"}],"21299":[{"meter":"4/4","mode":"Fmajor","abc":"|:c_d FGBA|c8-|c3FG3F|F8-|"},{"meter":"4/4","mode":"Dmajor","abc":"|:A_B DEGF|A8-|A3DE3D|D8-|"}],"21547":[{"meter":"12/8","mode":"Ddorian","abc":"|:A2 GF E2 G2 FD FG|A2 GF E2 G2 F2 D2:||:E2 DC B,2 D2 CA, CD|"},{"meter":"12/8","mode":"Ddorian","abc":"|:A2 GF E2 G2 FD FG|A2 GF E2 G2 F2 D2|E2 DC B,2 D2 CA, CD|"}],"21272":[{"meter":"9/8","mode":"Gdorian","abc":"|:D2G {A}GFG B2G|DFG GFG F/G/FC|D2G {A}GFG Bcd|1"},{"meter":"9/8","mode":"Adorian","abc":"|:E2A AGA c2A|EGA AGA GGD|E2A AGA cde|1"},{"meter":"9/8","mode":"Bdorian","abc":"|:F2B BAB d2B|FAB BAB A2E|F2B BAB def|1"}],"21585":[{"meter":"3/4","mode":"Dmajor","abc":".dd ef/g/ af|.ga bgaf|d2 ef/g/ .f.e|"},{"meter":"3/4","mode":"Fmajor","abc":"FF G/A/B cA|Bcd.B.c.A|F2 G/A/B .cA|"},{"meter":"3/4","mode":"Dmajor","abc":".DD EF/G/ AF|.GA BGAF|D2 EF/G/ .F.E|"},{"meter":"3/4","mode":"Fmajor","abc":"FF GA/B/ cA|Bc dB cA|F2 G A/B/ AG|"},{"meter":"3/4","mode":"Dmajor","abc":"DDE F/G/ AF|GAB GAF|D2 E F/G/FE|"}],"21380":[{"meter":"4/4","mode":"Bminor","abc":"|:BcBA B2c2|dcdc B2f2|BcBA BcAc|"},{"meter":"4/4","mode":"Bminor","abc":"|:B3 A ~B3 c|dcdc ~B3 A|BcBA BcAc|"}],"21780":[{"meter":"4/4","mode":"Gminor","abc":"D|:F4-FD CB,/D/-|D B,-B,3 F GF/B/-|B6 GG|"},{"meter":"4/4","mode":"Gminor","abc":"V:1\nD2|F4 D C2 B,|D B,4 FGA/B/-|B6 G3/A//G//|"}],"21702":[{"meter":"3/4","mode":"Amajor","abc":"cd|:e2 ed cd|ec A2 A/B/c|BG E2 GB|"},{"meter":"3/4","mode":"Gmajor","abc":"Bc|:d2 dc Bc|dB G2 (3GAB|AF D2 FA|"}],"21195":[{"meter":"12/8","mode":"Gmajor","abc":"|:g2e|\"G\" d2B G2D \"C\" E2D G2B|\"D\" ABA AGA \"G\" BdB \"D\" A2B|\"G\" d2B G2D \"C\" E2D G2B|"},{"meter":"12/8","mode":"Amajor","abc":"|:a2f|e2c A2E F2E A2c|B3 BAB c2B Bcd|e2c A2E F2E A2c|"}],"21379":[{"meter":"4/4","mode":"Fmajor","abc":"|:fg|affe fcAc|BABd g2 ga|bgaf (3gfe cA|"},{"meter":"4/4","mode":"Dmajor","abc":"|:de|\"D\"fd dc \"D/F#\"dA FA|\"G\"GF GB \"A\"e2 ef|\"G\"ge fd \"A\"(3edc AF|"}],"21243":[{"meter":"3/4","mode":"Gmajor","abc":"(3AdA|:G2 B2 d2|d2 (3BcB A2|G2 B2 d2|"},{"meter":"3/4","mode":"Gmajor","abc":"|:G2 B2 d2|d2 B2 A2|G2 B2 d2|"}],"21922":[{"meter":"6/8","mode":"Cmajor","abc":"a|:gec cBc|dcA A2B|cGE EDE|"},{"meter":"6/8","mode":"Dmajor","abc":"b|:afd dcd|edB B2c|dAF FEF|"}],"21883":[{"meter":"4/4","mode":"Dmajor","abc":"FE|:D2DF ABdf|D2DF EDB,A,|D2DF ABdf|1"},{"meter":"4/4","mode":"Dmajor","abc":"|:D2 DF ABdf|D2 DF ED B,2|D2 DF ABdf|"}],"21201":[{"meter":"6/8","mode":"Dminor","abc":"|:dDE FGA|fed c2A|cdc AGF|1"},{"meter":"6/8","mode":"Edorian","abc":"eEF GAB | gfe dBc | ded BAG |"}],"21451":[{"meter":"6/8","mode":"Amajor","abc":"|:A2e edd|dcc cBB|Bcc ece|"},{"meter":"6/8","mode":"Gmajor","abc":"|:G|GBd dcc|cBB BAA|GBd dBd|"}],"21266":[{"meter":"4/4","mode":"Cmajor","abc":"G|E2 G2 c3 G|A2 F2 d3 c|B2 A2 G2 F2|"},{"meter":"4/4","mode":"Gmajor","abc":"D|B,2 D2 G3 D|E2 C2 A3 G|F2 E2 D2 C2|"},{"meter":"4/4","mode":"Cmajor","abc":"G|E2 G2 c3 G|A2 F2 d3 c|B2 A2 G2 F2|"}],"21224":[{"meter":"6/8","mode":"Gmajor","abc":"D|:G2B BAB|GEF GBd|gfg dBG|"},{"meter":"6/8","mode":"Gmajor","abc":"D|:G2B BAB|GEF GB/c/d|g3 dBG|"}],"21384":[{"meter":"12/8","mode":"Eminor","abc":"D|:E3 B3 B2 B A3/2B1/2d|e5 e3 e2 B|c3 c2 B c2 B A3/2B1/2d|"},{"meter":"12/8","mode":"Fdorian","abc":"B |:c3 g3- g2 g g>fb | c'6- c'3 b2 g | a3- a2 g a2 g f>gb | g3- g2 e c3- c2 B | \nc3 g3- g2 g f>gb | c'6- c'3- c'2 d' | e'3- e'2 e' e'd'c' d'c'g | c'3- c'2 g c6 :|$ \n|:e3 g3- g2 g gfe | f3- f2 d B3- Bcd | e3- e2 d edc dcB | c6- c3- c2 d | $\ne3 g3- g2 g gfe | f3- f2 d B3 Bcd | e3- e2 d edc dcB | c3 c2 G c6 :|"}],"21608":[{"meter":"3/4","mode":"Dmajor","abc":"|:A de|f3 a f/e/d|B3 d cB|A2 d2 d/e/f|"},{"meter":"3/4","mode":"Dmajor","abc":"|:Ade|\"D\"f2 fa f/e/d|\"G\"B2 Bd cB|\"D\"A2 d2 d/e/f|"}],"21165":[{"meter":"4/4","mode":"Dmajor","abc":"|:A2|d2ddd2A2|e2eee2de|f2efg2f2|"},{"meter":"4/4","mode":"Dmajor","abc":"|:A|d2 dd d2 Ad|e2 ee e2 de|f2 ef g2 f2|"},{"meter":"4/4","mode":"Dmajor","abc":"|: AB | d2 dc d2 A/B/c/d/ | ed ef e2 A/B/d/e/ | f2 ef gf ed |"},{"meter":"4/4","mode":"Gmajor","abc":"|: D/E/F/ | G2 GF G2 D/E/F/G/ | AG ABA2 E/F/G/A/ | B2 ABcB AG |"}],"21607":[{"meter":"6/8","mode":"Gmajor","abc":"D/D/|DEF GAB|ced cBA|BGE DEG|"},{"meter":"6/8","mode":"Dmajor","abc":"d/B/|AB.d de.f|gb.a gf.e|fd.B AB.d|"},{"meter":"6/8","mode":"Gmajor","abc":"|:G/F/|DEG GAB|ced cBA|BGE DEG|"}],"21985":[{"meter":"6/8","mode":"Amixolydian","abc":"|:cBA ~A3|cee ~f2e|faa ~f2e|"},{"meter":"6/8","mode":"Amajor","abc":"|:cBA AAA|cdef2e|faa ece|"},{"meter":"6/8","mode":"Amajor","abc":"|:cBA ~A3|cee ~f2e|faa ~f2e|"}],"21738":[{"meter":"12/8","mode":"Dmajor","abc":"|:\"D\" F2 A ABA\"G\" G2 A B2 c|\"D\" d2 A ABA d2 A f2 A|F2 A ABA\"G\" G2 A B2 c||1"},{"meter":"12/8","mode":"Dmajor","abc":"\"D\" F2 A ABA\"G\" G2 A B2 d|\"A\" cBA e2f g2 e c2 A|\"D\"F2 A ABA\"G\" G2 A B2 d|"}],"21549":[{"meter":"6/8","mode":"Dmajor","abc":"(d3 .f)zz|e>d.e (f<d).B|.A.B.c .d2.b|(a>g).f {f}(e2d)|\nd3 .fzz|.e>.d.d (f<d).B|.A.B.c (d2.b)|.a>.g.f {f}.e.dz!fermata!||\n(f>g).a (a>b)=.c'|(bg).b (af).d|.f>.g.a .a.b=c'|b^a.c !fermata!d'2d|\n(df).a (d'>c/).b|(ag).f (f>e).d|(dA).d (dA).d|(fg).f {f}(e2d)||"},{"meter":"6/8","mode":"Gmajor","abc":"G3 B3|AGA BGE|DEG G2e|"},{"meter":"6/8","mode":"Fmajor","abc":"F3 A3|GFG AFD|CDF F2 d|"}],"21180":[{"meter":"6/8","mode":"Dmajor","abc":"DEF AFA|d/d/Bd edB|DEF AFA|"},{"meter":"6/8","mode":"Dmajor","abc":"DEF AFA|dBd edB|DEF AFA|"}],"21669":[{"meter":"4/4","mode":"Gmajor","abc":"|:B2AG GcBA|B2AG E2Dc|B2AG GcBA|"},{"meter":"4/4","mode":"Dmajor","abc":"|:f2ed dgfe|f2ed B2Ag|f2ed dgfe|"}],"21711":[{"meter":"6/8","mode":"Emajor","abc":"|:cBG FGB|~E3 EGB|cBG FGB|"},{"meter":"6/8","mode":"Dmajor","abc":"|:BAF EFA|~D3 DFA|BAF EFA|"}],"21612":[{"meter":"6/8","mode":"Bminor","abc":"c|d2d d2e|d3 c2B|A2B c2d|"},{"meter":"6/8","mode":"Dminor","abc":"|:F|F2 F F2 G|F3 E2 E|D2 D E2 F|"},{"meter":"6/8","mode":"Eminor","abc":"F|G2G G2A|G3 F2E|D2E F2G|"}],"21864":[{"meter":"4/4","mode":"Emajor","abc":"|:E2 BA GE E2|B,EGE CEAc|B2 Bc BGEG|"},{"meter":"4/4","mode":"Dmajor","abc":"|:D2 AG FD D2|A,DFD B,DGB|A2 AB AFDF|"}],"21372":[{"meter":"4/4","mode":"Dmajor","abc":"D2-|:DEFG AGFD|(3EFG AB ~=c2Bc|Ad ~d2 Adad|"},{"meter":"4/4","mode":"Dmajor","abc":"DEFG AGFD|E/F/GAB =c2 Bc|Ad d2 Adad|"},{"meter":"4/4","mode":"Dmajor","abc":"|:A,|DEFG AGFD|E/F/G AB =c/d/c Bc|Ad Rd2 Adad|eged cAGE|\nD2 E/F/G AGFD|E/F/G AB =c2 Bc|Ad Rd2 Adfd|1 cAGE EDD:|2 cAGE ED [D2A2]||\n|:fgag fdAG|F/G/F DF GE=CE|DFAd f/g/f ed|B/c/d ef g2 ag|\nfgag fdAG|F/G/F DF GE=CE|DFAd f/g/f ed|1 cAGE ED D2:|2 cAGE EDD||"}],"21373":[{"meter":"4/4","mode":"Gdorian","abc":"BDGA BDGB|AD^FA d2 {e}dc|BDGA BDGB|AdAG DGGA|\nBDGA BDGB|AD^FA d2 dc|(3=Bcd g^f gdBd|c2 =BG DGGA||\n[K:G] (3Bcd gd adgd|Bdgd cAAc|Bdad Bdgd|`~c2 BG DGGA|\n(3Bcd gd Bdgd|(3Bcd fa ~g3 a|bg ~g2 dcBd|~c2 BG DGGA||"},{"meter":"4/4","mode":"Gdorian","abc":"BDGA BDGB|AD^FA d2 dc|ABGA BDGB|"},{"meter":"4/4","mode":"Gmixolydian","abc":"|:A|_BDGA BDGB|AD^FA d2{e}dc|_BDGA BDGB|AdAG DGGA|\n_BDGA BDGB|AD^FA d2 dc|B/c/d g^f gdBd|c/d/c BG DGG:|\n|:A|B/c/d gd adgd|B/c/d gd cAAc|B/c/d ad B/c/d gd|c/d/c BG DGGA|\nBdgd adgd|B/c/d ^fa [B3g3] a|bg Rg2 dcBd|c/d/c BG DGG:|"}],"21229":[{"meter":"6/8","mode":"Cmajor","abc":"|:G|CEG A2 G|cGG AGF|EEE FEF|"},{"meter":"6/8","mode":"Dmajor","abc":"|:A|DFA B2 A|dAA BAG|FFF GFG|"}],"21356":[{"meter":"6/8","mode":"Dmixolydian","abc":"|:D|EAA ABc|BAB GED|EFG EFG|"},{"meter":"6/8","mode":"Dmixolydian","abc":"D|:EAA ABc|BAB GED|EFG EFG|"}],"21577":[{"meter":"4/4","mode":"Fmajor","abc":"|:cd/2e/2|fe dc f3 d|cAGF G2 AB|c2 AF BA GF|"},{"meter":"4/4","mode":"Dmajor","abc":"AB/c/|dc BA d3B|AF ED E2 FG|A2 FD GF {F}ED|"},{"meter":"4/4","mode":"Gmajor","abc":"def|gf ed g2 Ge|dB AG A2 Bc|d2 BG cB AG|"}],"21259":[{"meter":"4/4","mode":"Gmajor","abc":"|:gfed efge|dcBA Bcd2|gfed efge|"},{"meter":"4/4","mode":"Gmajor","abc":"|:\"G\"gfed \"C\"efge|\"D7\"dcBA \"G\"Bcd2|\"G\"gfed \"C\"efge|"}],"21964":[{"meter":"9/8","mode":"Adorian","abc":"|:A3A c cdc|B2 G G2 B d2 B|A2 c e2 g gag|f2 d d2 f a2 f|"},{"meter":"9/8","mode":"Adorian","abc":"|:A z2z2A c2c|B2B G2G BcB|A2c e3g3|"}],"21672":[{"meter":"2/4","mode":"Gmajor","abc":"gd dg|ef/e/ dc|BG GB|Ad fa|"},{"meter":"2/4","mode":"Gmajor","abc":"dz fz|:gd dg|ef/e/ dc|BG GB|"}],"21999":[{"meter":"6/8","mode":"Gminor","abc":"|:Bc|d^cd =cBA|G^FG B2 c|d/d/d^c d=ef|"},{"meter":"6/8","mode":"Gmajor","abc":"|:GA|BcB ABA|GED E2 A|B2A B^cd|"}],"21967":[{"meter":"9/8","mode":"Dmajor","abc":"M: 7/8\n|:D2 DE FED|AD BD AFD|G,B, DG FED|EF ED CB,A,|"},{"meter":"9/8","mode":"Dmajor","abc":"M: 7/8\n|:d2 de fed|ad bd afd|GB dg fed|ef ed cBA|"}],"21580":[{"meter":"6/8","mode":"Amixolydian","abc":"AcA GFG|ABc def|gfe def|"},{"meter":"6/8","mode":"Amixolydian","abc":"|:G|ABA GFG|ABc def|gbg faf|"},{"meter":"6/8","mode":"Gmajor","abc":"|:G3 D3|GAB cde|f3 ef/g/e|"},{"meter":"6/8","mode":"Dmixolydian","abc":"|:c|ded cBc|def g2B|cec Bdf|"}],"21035":[{"meter":"4/4","mode":"Dmajor","abc":"de|:\"D\"fdec dAFA|\"G\"GABG E2ed|\"A\"c2 (3BcB Acec|"},{"meter":"4/4","mode":"Dmajor","abc":"d2e2|:fdec dAFA|GABG E2ed|c2B2 Acec|"}],"21099":[{"meter":"3/4","mode":"Dmajor","abc":"|:f3e d2|e2 c2 A2|d3c B2|"},{"meter":"3/4","mode":"Dmajor","abc":"de | f3e d2 |e2c2A2 | d3c B2 |"}],"21301":[{"meter":"4/4","mode":"Gminor","abc":"|:GABc dgfd|Bcc/c/c cBAB|GABc dgfd|"},{"meter":"4/4","mode":"Gminor","abc":"|:GABc dgfd|Bcc/c/c cBAc|GABc dgfd|"}],"21327":[{"meter":"6/8","mode":"Aminor","abc":"|:EAA GAA|EAG AGD|EAA ABc|"},{"meter":"6/8","mode":"Eminor","abc":"|:Bee dee|Bed edA|Bee efg|"}],"21431":[{"meter":"9/8","mode":"Bminor","abc":"|:\"Bm\" FBc dcB dcB|FBc dcB \"A\"c2A|\"Bm\"FBc dcB dcB|1"},{"meter":"9/8","mode":"Bminor","abc":"|:\"Bm\"FBc dcB dcB|FBc dcB \"A\"A2G|\"Bm\"FBc dcB dcB|"},{"meter":"9/8","mode":"Aminor","abc":"|:\"Am\"EAB cBA cBA|EAB cBA \"G\"G2F|\"Am\"EAB cBA cBA|"}],"21210":[{"meter":"2/4","mode":"Ddorian","abc":"|:c2 df|e3 c|fe c2|A4|"},{"meter":"2/4","mode":"Adorian","abc":"|:G2 Ac|B3 G|cB G2|E4|"},{"meter":"2/4","mode":"Bdorian","abc":"|:A2 Bd|c3 A|dc A2|F4|"}],"21143":[{"meter":"3/4","mode":"Dminor","abc":"|:A2|d^cde fg|a2^c2a2|gfef ga|"},{"meter":"3/4","mode":"Eminor","abc":"|:B2|E^DEF GA|B2^D2B2|AGFG AB|"}],"21606":[{"meter":"3/2","mode":"Dmajor","abc":"|:DEFG AFDF EDEF|D2 EF GFED C2 C2|DEFG AFDF EDEF|"},{"meter":"3/2","mode":"Dmajor","abc":"|:AFDF GECE D2 EF|GFED C2 E2 DEFD|AFDF GECE D2d2|"},{"meter":"3/2","mode":"Gmajor","abc":"|:BAGB AGAB G2 G2|cBAG A2 d2 ABcA|BAGB AGAc B2 B2|"}],"21759":[{"meter":"6/8","mode":"Cmajor","abc":"G|:c2c cAG|cde egg|age edc|"},{"meter":"6/8","mode":"Gmajor","abc":"Bdd dBd|eef edd|ded dBA|"},{"meter":"6/8","mode":"Gmajor","abc":"|: G2 G GED | G2 G Bdd | edd dBA |"}],"21857":[{"meter":"4/4","mode":"Gmajor","abc":"d2|:(3gag (3ded (3BdB GB|dg gf gf ed|(3efg dB cB AG|"},{"meter":"4/4","mode":"Gmajor","abc":"|:(3gag fg (3BcB AB|GBdg gfgd|(3efg dB cBAG|"}],"21300":[{"meter":"4/4","mode":"Dmajor","abc":"|:A,DD/D/D EFED|~E2 DE FAA/A/A|A,DD/D/D EFED|"},{"meter":"4/4","mode":"Amajor","abc":"|:EAA/A/A BcBA|~B2 AB cee/e/e|EAA/A/A BcBA|"},{"meter":"4/4","mode":"Gmajor","abc":"|:DGG/G/G ABAG|~A2 GA Bdd/d/d|DGG/G/G ABAG|"}],"21682":[{"meter":"4/4","mode":"Gmajor","abc":"D|:(3GGG Bddd BG|EEAG FGAF|(3GGG Bdde ge|1"},{"meter":"4/4","mode":"Gmajor","abc":"D|:G2Bd ddBG|EEAG FGAF|G2Bd dege|1"},{"meter":"4/4","mode":"Gmajor","abc":"|:G2Bd deBG|EGAG FGAF|G2Bd dege|1"}],"21484":[{"meter":"4/4","mode":"Cmajor","abc":"cA|:GEDG ECCA|GCEG Acde|cAAG GAAG|"},{"meter":"4/4","mode":"Dmajor","abc":"dB|:AFEA FDDB|ADFA Bdef|dBBA ABBA|"}],"21341":[{"meter":"4/4","mode":"Dmajor","abc":"|:DE|F3 A ^G2 e2|dcBA d3 F|G3 A/B/ A2 F2|"},{"meter":"4/4","mode":"Dmajor","abc":"|:DE|F3 A ^G2 e2|dcBA d3 F|G3 A/B/ A2 F2|"}],"21832":[{"meter":"4/4","mode":"Dmixolydian","abc":"|:(3ABA GB AD~D2|AEGE C3 E|DAFA dfed|"},{"meter":"4/4","mode":"Dmixolydian","abc":"|:A2 GB AD D2|AEGE C3 z|DAFA dfed cAGE ADEG|"}],"21697":[{"meter":"4/4","mode":"Dmajor","abc":"|:F3 D E/F/GF2|FE F/E/D {F}EDB,A,|DA,FB, DGF2|"},{"meter":"4/4","mode":"Dmajor","abc":"|:f3 d e/f/gf2|fe f/e/d {f}edBA|dAfB dgf2|"},{"meter":"4/4","mode":"Dmajor","abc":"|:f3 d e/f/gf2|fe f/e/d {f}edBA|dAfB dgf2|"}],"21033":[{"meter":"6/8","mode":"Gmixolydian","abc":"d2d B2G|d2d BAG|dBd g2B|"},{"meter":"6/8","mode":"Amixolydian","abc":"e2e c2A|e2e cBA|ece a2c|"}],"21844":[{"meter":"4/4","mode":"Gminor","abc":"K:Bb\n|:B2 fe dfcB|Bccc defg|B2 fe dfcB|1"},{"meter":"4/4","mode":"Amajor","abc":"|:e|AAeA c2 BA|BBBB d2 f2|AAeA c2 BA|"},{"meter":"4/4","mode":"Amixolydian","abc":"|:eAAe AccB|ABBB Bddf|eAAe AccB|1"},{"meter":"4/4","mode":"Bminor","abc":"|:B2fe dfcA|Bcde fgfd|B2fe dfcA|1"}],"21686":[{"meter":"6/8","mode":"Gmajor","abc":"G/2A/2|B3/2A/2G AGE|D3E2G|GAB c2B|"},{"meter":"6/8","mode":"Dmajor","abc":"|:d/e/|fe.d ed.B|A3 B2.d|de.f ag.f|"}],"21876":[{"meter":"2/4","mode":"Amajor","abc":"|:(3 e/f/a/|aA AB|ce ab/a/|ge e/f/g/a/|"},{"meter":"2/4","mode":"Dmajor","abc":"A|:\"D\" dD DE|FA de/d/|\"A\" cA A/B/c/d/|"}],"21578":[{"meter":"3/4","mode":"Gmajor","abc":"d/e/f/|g4 ge|d3 cBA|G4 BG|"},{"meter":"3/4","mode":"Dmajor","abc":"A/B/c|d4 dB|A3 GFE|D4 FD|"},{"meter":"3/4","mode":"Dmajor","abc":"F|d4 dB|A3 G FE|D4 FD|"}],"21409":[{"meter":"6/8","mode":"Bminor","abc":"|:A,|B,DF BFB|AGF DEF|GBd c2 B|"},{"meter":"6/8","mode":"Bminor","abc":"|:A|Bdf B2 B|AGF DEF|GBd c2 B|"}],"21054":[{"meter":"6/8","mode":"Dmajor","abc":"|:ABA AcA|AdA f2e|1 a2 e fec|"},{"meter":"6/8","mode":"Dmajor","abc":"|:ABA AcA|AdA f2e|1 a2 e fec|"}],"21939":[{"meter":"6/8","mode":"Eminor","abc":"|:EF|\"G\" GFG \"D\" AGA|\"G\" B4 Bc|\"G\" dcB \"D\" AGA|"},{"meter":"6/8","mode":"Cmajor","abc":"V:1\nA|cBc dcd|e3cde|f2e dcd|"},{"meter":"6/8","mode":"Gmajor","abc":"GA|BcB BcA|GAG GAB|cdc Bcd|"}],"21657":[{"meter":"4/4","mode":"Amajor","abc":"|:cd|eaaa e2cd|eaaa e2cd|eaaa edcA|"},{"meter":"4/4","mode":"Amajor","abc":"|:cd|eafa ecAc|eafa e2cd|eafa ecAc|"}],"21156":[{"meter":"4/4","mode":"Gmajor","abc":"|:Bc|dBcA GBdg|fe^de a3 g|fgfe dcAF|"},{"meter":"4/4","mode":"Gmajor","abc":"|:Bc|dBcA GBdg|fe^de a3 g|fgfe dcAF|"}],"21655":[{"meter":"6/8","mode":"Dmajor","abc":"de|:f2f efa|d3-def|gfe dcB|"},{"meter":"6/8","mode":"Gmajor","abc":"|:B2B ABd|G3 -GAB|cBA GFE|"}],"21524":[{"meter":"9/8","mode":"Amajor","abc":"|:A3 ABc ecB|A3 Ace f2e|c2e cBA F2E|"},{"meter":"9/8","mode":"Gmajor","abc":"|:G3 GAB dBA|G3 GBd e2d|B2d BAG E2D|"}],"21245":[{"meter":"9/8","mode":"Edorian","abc":"EF|:GEE eBc dcB|AdB AFD DEF|GEE eBc dcB|1"},{"meter":"9/8","mode":"Edorian","abc":"|:F|GEE eBc dcB|AdB AFD DEF|GEE eBc dcB|"}],"21335":[{"meter":"4/4","mode":"Gminor","abc":"d|:GG dc dg g2|fc df cB AF|GG dc {c}Ac dg|"},{"meter":"4/4","mode":"Gminor","abc":"|:g|GG dc df g2|!turn!fc df TcB AF|GG dc AcdG|"}],"21262":[{"meter":"4/4","mode":"Adorian","abc":"|:AB ce|Ae ed/B/|GA Bd|Gd dB|"},{"meter":"4/4","mode":"Adorian","abc":"|:AB ce|Ae ed/B/|GA Bd|Gd dc/B/|"}],"21645":[{"meter":"3/4","mode":"Gmajor","abc":"|:GA|B2dB c/B/A/G/|EF GG FE||DE GD dB|"},{"meter":"3/4","mode":"Dmajor","abc":"d>e|:f2 a>f g/f/e/d/|B2 d>d cB|A>B dA a>f|[M:2/4]e2 d>e|\n[M:3/4]f2 a>f g/f/e/d/|B2 d>d cB|A>B dA f>e|1 [M:2/4]d2 d>e:|2 [M:2/4]d2 e>d||\n[M:3/4]ce A2 a>g|fs d2 ed|[M:2/4]ce dB|A2 d>e||\n[M:3/4]f2 a>f g/f/e/d/|B2 d>d cB|A>B dA a>f|[M:2/4]e2 d>e|\n[M:3/4]f2 a>f g/f/e/d/|B2 d>d cB|A>B dA f>e|d4||"},{"meter":"3/4","mode":"Gmajor","abc":"D GA|:B2 d>B c/B/A/G/|EE/F/ G2 FE|DD/E/ GD dB|A3 D GA|\nB2 d>B c/B/A/G/|EE/F/ G2 FE|DD/E/ GD B>A|1 G3D GA:|2 G4 AG|\nF<A D2 d>c|B<d G2 AG|F<A D2 dc|B3 B A>G|\nF<A D2 dc|B<d G2 A>G|[M:2/4]F<A G<E|[M:3/4]D3 D GA||\nB2 d>B c/B/A/G/|EE/F/ G2 FE|DD/E/ GD dB|A3 D GA|\nB2 d>B c/B/A/G/|EE/F/ G2 FE|DD/E/ GD B>A|G3||"}],"21064":[{"meter":"9/8","mode":"Dmajor","abc":"d2B BBB BAG|ddd ged e2d|d2B BBB BAG|ged BAG B3|"},{"meter":"9/8","mode":"Dmajor","abc":"d2B BBB BAG|ddd ged e2d|d2B BBB BAG|ged BAG B3|"}],"21246":[{"meter":"6/8","mode":"Eminor","abc":"|:EFG GAB|AFG EFD|EGB edc|"},{"meter":"6/8","mode":"Eminor","abc":"|:EFG AGF|AFG EFD|EGB edc|"},{"meter":"6/8","mode":"Eminor","abc":"|:EGB AGF|AFG EFD|EGB edc|"}],"21398":[{"meter":"6/8","mode":"Dmajor","abc":"|:dcB|A2 A ABc|dAA Adc|BBB Bcd|"},{"meter":"6/8","mode":"Dmajor","abc":"|:FAA ABc|dAA A3|BBB Bcd|"}],"21871":[{"meter":"6/8","mode":"Eminor","abc":"|:GBB GBB|FAA FAA|GBB BBA|"},{"meter":"6/8","mode":"Eminor","abc":"|:EBB EBB|DAA DAA|EBB BBA|"},{"meter":"6/8","mode":"Dminor","abc":"|:FAA FAA|EGG EGG|FAA FAA|"}],"21773":[{"meter":"4/4","mode":"Fmajor","abc":"|:\"F\"fg ag fd cA|\"F/A\" G2 .A2 A3 B-|\"Bb\" B2 F2 d2 cB|"},{"meter":"4/4","mode":"Fmajor","abc":"\"F\"fg ag fd cA| G2 .A2 A2 (3FGA|\"Bb\" B2 B2 d2 cB|"}],"21102":[{"meter":"4/4","mode":"Gmajor","abc":"|:G2GF GBBA|GA (3BAG g2 ef|gage dBGA|"},{"meter":"4/4","mode":"Gmajor","abc":"|:(3DEF |G2 GF GBdB|GBdB g2 (3def | gage dBGB|"}],"21342":[{"meter":"4/4","mode":"Gmajor","abc":"|:GA|B2 Bc dcBA|B2 G2 G2 AB|cBcd edcB|"},{"meter":"4/4","mode":"Dmajor","abc":"|:FG|A^GAB A=GFE|F2 D2 D2 EF|GFGA BAGF|"}],"21222":[{"meter":"4/4","mode":"Bmixolydian","abc":"|:BcBG B2 Bc|B2 gf eBBB|c2fg fccf|"},{"meter":"4/4","mode":"Amajor","abc":"|:ABAF A2 AB|A2 fe dAAA|B2ef eBBe|"}],"21238":[{"meter":"6/8","mode":"Adorian","abc":"|:E2B AGE-|EBA Bd2|BA2 GEA|"},{"meter":"6/8","mode":"Adorian","abc":"|:A2 e ede|g2{/ag} e edB|A2 e{/f} ede|g.a/ z/ g edB|\nA2 e ede|g2{/ag} e edB|ege z{/f} ed|eg{/a}g edB:|\n|:A2 c BAG|ADE G2 A|z2 c BAG|AdB{/c} BAG|\nA2 c BAG|ADE G2 A|cBB GAA|cBG ABG:|\n|:E2 B AGE|z BA Bd z|{/A} BA z GEA|{/A} GEE DEG|\nE2 B{/B} AGE|z BA Bd z|{/d} ed z BAG|AGE DEG:|\n|:A2 e ede|{/e} g2 e d2 B|gef dec|dBc BAG|\nE2 B{/c} AGA|{/c} BAG EFD|E2 B{/B} AGA|BdB d2 e:|\n|:A2 c BAG|ADE G2 A|c BBG AA|cBG ABG|\nE2 B{/c} AGA|{/c} BAG EFD|E2 B{/B} AGA|1 BdB d2 e:|2 Bde{/e} gfd||\n|:e z b age|z ba gea|{/e} fed g2 d|BcA BAG|\nE2 B{/B} AGA|BdB edB|ABd ege|fed{/g} afd:|"},{"meter":"6/8","mode":"Adorian","abc":"|:A2 e ede|g2e edB|A2e ede|"}],"21973":[{"meter":"4/4","mode":"Amixolydian","abc":"|:EA (3ABA A=cEF|G2DG B,DGF|E~A,3 G,B,Dd|"},{"meter":"4/4","mode":"Amixolydian","abc":"|:EA (3ABA A=cEF|G2DG BdGF|E~A3 GBd2|"}],"21786":[{"meter":"6/8","mode":"Dmajor","abc":"|:DFA d2A|d2A BAF|DFA dfe|"},{"meter":"6/8","mode":"Cmajor","abc":"|:CEG c2G|A2G AGE|CEG ced|"}],"21083":[{"meter":"3/4","mode":"Bminor","abc":"|:dB F2 E2|DC B,2 CB,|A,3 B, CE|"},{"meter":"3/4","mode":"Bminor","abc":"|:dB F2 E2|dc b,2 cB|A3 B de|"}],"21098":[{"meter":"4/4","mode":"Dmajor","abc":"A2 DE FGAB|=cAed ^cdeg|f2 (3gfe agec|"},{"meter":"4/4","mode":"Dmajor","abc":"|:\"D\" A2 DE FGAB|\"Am\"=cAed \"A\"^cdeg|\"D\"f2 (3gfe \"A\"agec|"}],"21930":[{"meter":"3/4","mode":"Emajor","abc":"|:b3 g bg|a3 c' ba|ga fg ef|"},{"meter":"3/4","mode":"Emajor","abc":"|:b3 g bg|a3 c' ba|ga fg ef|"}],"21631":[{"meter":"3/4","mode":"Gmajor","abc":"GA|B4 ed|d2 D2 BA|G6|"},{"meter":"3/4","mode":"Gmajor","abc":"GA|:B4 de|d4 BA|G6|"},{"meter":"3/4","mode":"Gmajor","abc":"GA|:B4 ed/e/|d4 B3/A/|G6|"},{"meter":"3/4","mode":"Gmajor","abc":"GA|:B4 ed|d4 BA|G6|g4 f/g/f|\ne4 fg|dB3 AG|A6-|A4 GA|\nB4 ed|d4 BA|G6|e2 f3 g|dB3 (3BAG|\nA3 G F2|G6-|1 G3 DGA:|2 G4 g2||\ng3 a/g/ f2|g3a bd|e4 Re2|d3 def|\ng4 B2|B4 AG|A6-|A4 g2|\ng3 a/g/ f2|g2za bd|e4 Re2|d4 ge|\ndB3 AG|A3 B/A/ GF|G6-|G4||"}],"21450":[{"meter":"3/4","mode":"Cmajor","abc":"G,2|E2 E2 ED|C4 G,G,|F2 F2 E2|"},{"meter":"3/4","mode":"Gmajor","abc":"D2|B2 B2 BA|G4 DD|c2 c2 B2|"}],"21916":[{"meter":"9/8","mode":"Amajor","abc":"cee efc eeA|cee efc cBB|cee efe ecB|"},{"meter":"9/8","mode":"Gmajor","abc":"|Bdd deB d2 A|Bdd deB BAA|Bdd deB dBA|"}],"21215":[{"meter":"4/4","mode":"Gminor","abc":"|:G/A/|BffB A3 B/A/|GFFD F3 G/A/|BABc A3 G/F/|"},{"meter":"4/4","mode":"Aminor","abc":"|:A/B/|cggc B3 c/B/|AGGE G3 A/B/|cBcd B3 A/G/|"},{"meter":"4/4","mode":"Eminor","abc":"|:E/F/|GddG F3 G/F/|EDDB D3 E/F/|GFGA F3 E/D/|"}],"21270":[{"meter":"4/4","mode":"Eminor","abc":"|:E2 E2 EFGE|FGFE D2 B,2|B2-B2 ABAG|"},{"meter":"4/4","mode":"Bminor","abc":"|:B2 B2 BcdB|cdcB A2 F2|f2-f2 efed|"}],"21060":[{"meter":"3/4","mode":"Amixolydian","abc":"|:dc B2 F2|ED EF AF|dc B2 F2|"},{"meter":"3/4","mode":"Fmajor","abc":"|:fe df A2|GF GA cA|fe df A2|"},{"meter":"3/4","mode":"Amixolydian","abc":"|:dc Bd F2|ED EF AF|dc Bd F2|"}],"21613":[{"meter":"4/4","mode":"Dminor","abc":"DE|G2G3/2A/2 GEDE|G2G3/2A/2 GEDE|A2A3/2B/2 c2E3/2F/2|"},{"meter":"4/4","mode":"Aminor","abc":"DE|G2 GA GEDE|G2 GA GEDE|A2 AB c2 EF|"},{"meter":"4/4","mode":"Bminor","abc":"EF|A2 AB AFEF|A2 AB AFEF|B2 Bc d2 FG|"}],"21282":[{"meter":"4/4","mode":"Ddorian","abc":"|:DA,A, D2 C EC|DDFD ~E2 DC|~A,3 D EDCD|"},{"meter":"4/4","mode":"Ddorian","abc":"|:\"Dm\"DA,A, D2 C EC|\"Dm\"DDFD ~E2 DC|\"Dm\"A,2 A,D EDCD|"}]}